paragraphs/__init__.py
paragraphs/main.py
paragraphs/py.typed
paragraphs-1.0.1.dist-info/LICENSE.txt
paragraphs-1.0.1.dist-info/METADATA
paragraphs-1.0.1.dist-info/WHEEL
paragraphs-1.0.1.dist-info/top_level.txt
paragraphs-1.0.1.dist-info/RECORD
