Metadata-Version: 2.1
Name: paragraphs
Version: 1.0.1
Summary: Incorporate long strings painlessly, beautifully into Python code.
Author-email: Shay Hill <shay_public@hotmail.com>
License: MIT
Requires-Python: >=3.8
License-File: LICENSE.txt
Provides-Extra: dev
Requires-Dist: commitizen; extra == "dev"
Requires-Dist: pre-commit; extra == "dev"
Requires-Dist: pytest; extra == "dev"
Requires-Dist: tox; extra == "dev"
